MANIFEST.in
README.md
setup.py
src/flask_validation/__init__.py
src/flask_validation/validation.py
src/li_flask_validation.egg-info/PKG-INFO
src/li_flask_validation.egg-info/SOURCES.txt
src/li_flask_validation.egg-info/dependency_links.txt
src/li_flask_validation.egg-info/requires.txt
src/li_flask_validation.egg-info/top_level.txt